<?xml version="1.0" encoding="utf-8"?>

<Deployment xmlns="http://schemas.microsoft.com/windowsphone/2012/deployment" AppPlatformVersion="8.0">
  <DefaultLanguage xmlns="" code="en-US"/>
  <App xmlns="" ProductID="{a9dffc5a-7e16-4702-b6c3-c1c2dcf10bfe}" Title="XML2DB" RuntimeType="Silverlight" Version="1.0.0.0" Genre="apps.normal"  Author="XML2DB author" Description="Sample description" Publisher="XML2DB" PublisherID="{85f66deb-3f4f-4ee0-8eb7-0b701641dab1}">
    <IconPath IsRelative="true" IsResource="false">Assets\ApplicationIcon.png</IconPath>
    <Capabilities>
      <Capability Name="ID_CAP_NETWORKING"/>
      <Capability Name="ID_CAP_MEDIALIB_AUDIO"/>
      <Capability Name="ID_CAP_MEDIALIB_PLAYBACK"/>
      <Capability Name="ID_CAP_SENSORS"/>
      <Capability Name="ID_CAP_WEBBROWSERCOMPONENT"/>
    </Capabilities>
    <Tasks>
      <DefaultTask  Name ="_default" NavigationPage="MainPage.xaml"/>
    </Tasks>
    <Tokens>
      <PrimaryToken TokenID="XML2DBToken" TaskName="_default">
        <TemplateFlip>
          <SmallImageURI IsRelative="true" IsResource="false">Assets\Tiles\FlipCycleTileSmall.png</SmallImageURI>
          <Count>0</Count>
          <BackgroundImageURI IsRelative="true" IsResource="false">Assets\Tiles\FlipCycleTileMedium.png</BackgroundImageURI>
          <Title>XML2DB</Title>
          <BackContent></BackContent>
          <BackBackgroundImageURI></BackBackgroundImageURI>
          <BackTitle></BackTitle>
          <DeviceLockImageURI></DeviceLockImageURI>
          <HasLarge></HasLarge>
        </TemplateFlip>
      </PrimaryToken>
    </Tokens>
    <ScreenResolutions>
      <ScreenResolution Name="ID_RESOLUTION_WVGA"/>
      <ScreenResolution Name="ID_RESOLUTION_WXGA"/>
      <ScreenResolution Name="ID_RESOLUTION_HD720P"/>
    </ScreenResolutions>
  </App>
</Deployment>